<?xml version="1.0" encoding="utf-8"?>
<annotation>
	<folder>images</folder>
	<filename>shhh164.jpg</filename>
	<size>
		<width>500</width>
		<height>650</height>
		<depth>3</depth>
	</size>
	<segmented>0</segmented>
	<object>
		<name>sea_river</name>
		<pose>Unspecified</pose>
		<truncated>0</truncated>
		<difficult>0</difficult>
		<bndbox>
			<xmin>18</xmin>
			<ymin>296</ymin>
			<xmax>489</xmax>
			<ymax>463</ymax>
		</bndbox>
	</object>
	<object>
		<name>mountain</name>
		<pose>Unspecified</pose>
		<truncated>0</truncated>
		<difficult>0</difficult>
		<bndbox>
			<xmin>217</xmin>
			<ymin>19</ymin>
			<xmax>483</xmax>
			<ymax>181</ymax>
		</bndbox>
	</object>
</annotation>
